aer_plugin/__init__.py
aer_plugin/backends.txt
aer_plugin/config.py
aer_plugin/interface.py
aer_plugin/plugin.py
aer_plugin/backends/__init__.py
aer_plugin/backends/aer.py
aer_plugin/backends/base_backend.py
aer_plugin-0.0.2.dist-info/licenses/LICENSE
aer_plugin-0.0.2.dist-info/METADATA
aer_plugin-0.0.2.dist-info/WHEEL
aer_plugin-0.0.2.dist-info/top_level.txt
aer_plugin-0.0.2.dist-info/RECORD
