Metadata-Version: 2.4
Name: aer_plugin
Version: 0.0.2
Summary: A quantum plugin for qiskit AER
Home-page: https://github.com/Dpbm/aer-plugin
Author: Dpbm
Author-email: dpbm136@gmail.com
License: MIT
Classifier: Programming Language :: Python
Classifier: Programming Language :: Python :: 3
Classifier: Programming Language :: Python :: 3.0
Classifier: Programming Language :: Python :: 3.12
Classifier: Topic :: Scientific/Engineering
Classifier: Topic :: Scientific/Engineering :: Quantum Computing
Classifier: Topic :: Software Development
Classifier: Topic :: Software Development :: Libraries
Classifier: Topic :: System
Classifier: Topic :: System :: Hardware
License-File: LICENSE
Requires-Dist: qiskit-aer==0.17.0
Requires-Dist: qiskit==1.3.2
Requires-Dist: qiskit_qasm3_import
Dynamic: author
Dynamic: author-email
Dynamic: classifier
Dynamic: description
Dynamic: description-content-type
Dynamic: home-page
Dynamic: license
Dynamic: license-file
Dynamic: requires-dist
Dynamic: summary
